petisco/VERSION
petisco/__init__.py
petisco/public_api.py
petisco/py.typed
petisco/base/__init__.py
petisco/base/application/__init__.py
petisco/base/application/application.py
petisco/base/application/application_configurer.py
petisco/base/application/application_info.py
petisco/base/application/chaos/__init__.py
petisco/base/application/chaos/chaos_config.py
petisco/base/application/chaos/check_chaos.py
petisco/base/application/controller/__init__.py
petisco/base/application/controller/async_controller.py
petisco/base/application/controller/controller.py
petisco/base/application/controller/error_map.py
petisco/base/application/controller/handlers.py
petisco/base/application/controller/http_error.py
petisco/base/application/controller/meta_controller.py
petisco/base/application/dependency_injection/__init__.py
petisco/base/application/dependency_injection/container.py
petisco/base/application/dependency_injection/dependency.py
petisco/base/application/handlers/__init__.py
petisco/base/application/handlers/message_handler.py
petisco/base/application/middleware/__init__.py
petisco/base/application/middleware/middleware.py
petisco/base/application/middleware/notifier_middleware.py
petisco/base/application/middleware/print_middleware.py
petisco/base/application/notifier/__init__.py
petisco/base/application/notifier/not_implemented_notifier.py
petisco/base/application/notifier/notifier.py
petisco/base/application/notifier/notifier_exception_message.py
petisco/base/application/notifier/notifier_message.py
petisco/base/application/patterns/__init__.py
petisco/base/application/patterns/app_service.py
petisco/base/application/patterns/async_app_service.py
petisco/base/application/patterns/crud_repository.py
petisco/base/application/patterns/inmemory_crud_repository.py
petisco/base/application/patterns/repository.py
petisco/base/application/use_case/__init__.py
petisco/base/application/use_case/async_use_case.py
petisco/base/application/use_case/meta_use_case.py
petisco-2.2.3.dist-info/LICENSE
petisco-2.2.3.dist-info/METADATA
petisco-2.2.3.dist-info/WHEEL
petisco-2.2.3.dist-info/entry_points.txt
petisco-2.2.3.dist-info/top_level.txt
petisco-2.2.3.dist-info/RECORD
